{"singlePage": [], "startSite": "", "filingNum": "", "onePageListNum": 15, "commentLabelColor": "#006b75", "yearColorList": ["#bc4c00", "#0969da", "#1f883d", "#A333D0"], "i18n": "CN", "themeMode": "manual", "dayTheme": "light", "nightTheme": "dark", "urlMode": "pinyin", "script": "", "style": "", "head": "", "indexScript": "", "indexStyle": "", "bottomText": "", "showPostSource": 1, "iconList": {}, "UTC": 8, "rssSplit": "sentence", "exlink": {}, "needComment": 1, "allHead": "", "title": "\u79e6\u4ee5\u5b81\u7684\u535a\u5ba2", "subTitle": "Qin YiNing's blog.", "avatarUrl": "https://avatars.githubusercontent.com/u/172038171?v=4", "GMEEK_VERSION": "last", "postListJson": {"P1": {"htmlDir": "docs/post/jin-tian-dao-le-tai-guo.html", "labels": ["documentation"], "postTitle": "\u4eca\u5929\u5230\u4e86\u6cf0\u56fd", "postUrl": "post/jin-tian-dao-le-tai-guo.html", "postSourceUrl": "https://github.com/qinyining101/qinyining101.github.io/issues/1", "commentNum": 0, "wordCount": 104, "description": "https://github.com/user-attachments/assets/f608ec56-1295-4849-827c-b875c15ffe44\r\n\r\n2024/8/2 17:03(GMT+7)\u3002", "top": 0, "createdAt": 1722593116, "style": "", "script": "", "head": "", "ogImage": "https://avatars.githubusercontent.com/u/172038171?v=4", "createdDate": "2024-08-02", "dateLabelColor": "#bc4c00"}, "P2": {"htmlDir": "docs/post/ha-ha-ha-ha-ha.html", "labels": ["\u65e5\u5e38"], "postTitle": "\u54c8\u54c8\u54c8\u54c8\u54c8", "postUrl": "post/ha-ha-ha-ha-ha.html", "postSourceUrl": "https://github.com/qinyining101/qinyining101.github.io/issues/2", "commentNum": 0, "wordCount": 41, "description": "\u65e5\u5e38\u7684\u4e00\u5929\uff0c\u5728\u6cf0\u56fd\u5ea6\u5047\u3002", "top": 0, "createdAt": 1722687715, "style": "", "script": "", "head": "", "ogImage": "https://avatars.githubusercontent.com/u/172038171?v=4", "createdDate": "2024-08-03", "dateLabelColor": "#bc4c00"}}, "singeListJson": {}, "labelColorDict": {"bug": "#d73a4a", "documentation": "#0075ca", "duplicate": "#cfd3d7", "enhancement": "#a2eeef", "good first issue": "#7057ff", "help wanted": "#008672", "invalid": "#e4e669", "question": "#d876e3", "wontfix": "#ffffff"}, "displayTitle": "\u79e6\u4ee5\u5b81\u7684\u535a\u5ba2", "faviconUrl": "https://avatars.githubusercontent.com/u/172038171?v=4", "ogImage": "https://avatars.githubusercontent.com/u/172038171?v=4", "primerCSS": "<link href='https://mirrors.sustech.edu.cn/cdnjs/ajax/libs/Primer/21.0.7/primer.css' rel='stylesheet' />", "homeUrl": "https://qinyining101.github.io", "prevUrl": "disabled", "nextUrl": "disabled"}